[
  {
    "id": "669e2f3be1a63c1a80ebe00a",
    "documentType": "Dokument",
    "travelType": "Tåg",
    "departureDateTime": "2024-09-02T20:20:00",
    "travelFrom": "Florida",
    "travelTo": "Ecuador",
    "price": 3945,
    "travelTime": "04:31:00",
    "information": "SOVALKOV",
    "vehicleNumber": "T21",
    "hoursDelayed": null,
    "arrivalDateTime": null,
    "delayed": false
  },
  {
    "id": "669e2f3be1a63c1a80ebe00d",
    "documentType": "Dokument",
    "travelType": "Båt",
    "departureDateTime": "2024-09-01T20:00:00",
    "travelFrom": "Sverige",
    "travelTo": "Polen",
    "price": 1160,
    "travelTime": "08:20:00",
    "information": "VALFRI PLATS",
    "vehicleNumber": "B654",
    "hoursDelayed": null,
    "arrivalDateTime": null,
    "delayed": false
  },
  {
    "id": "669e2f3be1a63c1a80ebe00e",
    "documentType": "Dokument",
    "travelType": "Buss",
    "departureDateTime": "2024-09-02T04:20:00",
    "travelFrom": "Polen",
    "travelTo": "Tyskland",
    "price": 619,
    "travelTime": "11:15:00",
    "information": "VALFRI PLATS",
    "vehicleNumber": "A321",
    "hoursDelayed": null,
    "arrivalDateTime": null,
    "delayed": false
  },
  {
    "id": "669e2f3be1a63c1a80ebe011",
    "documentType": "Dokument",
    "travelType": "Flyg",
    "departureDateTime": "2024-09-03T11:40:00",
    "travelFrom": "Marocko",
    "travelTo": "Venezuela",
    "price": 1345,
    "travelTime": "09:50:00",
    "information": "17B",
    "vehicleNumber": "FH5TT",
    "hoursDelayed": null,
    "arrivalDateTime": null,
    "delayed": false
  },
  {
    "id": "669e2f3be1a63c1a80ebe014",
    "documentType": "Dokument",
    "travelType": "Flyg",
    "departureDateTime": "2024-09-03T22:30:00",
    "travelFrom": "Mexiko",
    "travelTo": "Sverige",
    "price": 23453,
    "travelTime": "13:20:00",
    "information": "1F",
    "vehicleNumber": "F123JG",
    "hoursDelayed": null,
    "arrivalDateTime": null,
    "delayed": false
  },
  {
    "id": "669e2f3be1a63c1a80ebe009",
    "documentType": "Dokument",
    "travelType": "Flyg",
    "departureDateTime": "2024-09-02T08:55:00",
    "travelFrom": "Portugal",
    "travelTo": "Florida",
    "price": 5430,
    "travelTime": "11:25:00",
    "information": "21A",
    "vehicleNumber": "FYJ23D",
    "hoursDelayed": null,
    "arrivalDateTime": null,
    "delayed": false
  },
  {
    "id": "669e2f3be1a63c1a80ebe00b",
    "documentType": "Dokument",
    "travelType": "Båt",
    "departureDateTime": "2024-09-01T21:35:00",
    "travelFrom": "England",
    "travelTo": "Portugal",
    "price": 1800,
    "travelTime": "11:20:00",
    "information": "VALFRI PLATS",
    "vehicleNumber": "B6655",
    "hoursDelayed": null,
    "arrivalDateTime": null,
    "delayed": false
  },
  {
    "id": "669e2f3be1a63c1a80ebe00c",
    "documentType": "Dokument",
    "travelType": "Flyg",
    "departureDateTime": "2024-09-02T19:30:00",
    "travelFrom": "Senegal",
    "travelTo": "Ecuador",
    "price": 19432,
    "travelTime": "08:30:00",
    "information": "4D",
    "vehicleNumber": "FLKO12P",
    "hoursDelayed": null,
    "arrivalDateTime": null,
    "delayed": false
  },
  {
    "id": "669e2f3be1a63c1a80ebe017",
    "documentType": "Dokument",
    "travelType": "Båt",
    "departureDateTime": "2024-09-02T04:17:00",
    "travelFrom": "Polen",
    "travelTo": "Frankrike",
    "price": 3201,
    "travelTime": "14:10:00",
    "information": "VALFRI PLATS",
    "vehicleNumber": "B99",
    "hoursDelayed": null,
    "arrivalDateTime": null,
    "delayed": false
  },
  {
    "id": "669e2f3be1a63c1a80ebe010",
    "documentType": "Dokument",
    "travelType": "Flyg",
    "departureDateTime": "2024-09-01T17:00:00",
    "travelFrom": "Sverige",
    "travelTo": "England",
    "price": 2768,
    "travelTime": "04:35:00",
    "information": "6F",
    "vehicleNumber": "FJC223",
    "hoursDelayed": null,
    "arrivalDateTime": null,
    "delayed": false
  },
  {
    "id": "669e2f3be1a63c1a80ebe013",
    "documentType": "Dokument",
    "travelType": "Båt",
    "departureDateTime": "2024-09-03T00:55:00",
    "travelFrom": "Frankrike",
    "travelTo": "Marocko",
    "price": 760,
    "travelTime": "10:45:00",
    "information": "VALFRI PLATS",
    "vehicleNumber": "B0012",
    "hoursDelayed": null,
    "arrivalDateTime": null,
    "delayed": false
  },
  {
    "id": "669e2f3be1a63c1a80ebe015",
    "documentType": "Dokument",
    "travelType": "Flyg",
    "departureDateTime": "2024-09-03T18:27:00",
    "travelFrom": "Frankrike",
    "travelTo": "Marocko",
    "price": 1233,
    "travelTime": "03:30:00",
    "information": "C3",
    "vehicleNumber": "F654J",
    "hoursDelayed": null,
    "arrivalDateTime": null,
    "delayed": false
  },
  {
    "id": "669e2f3be1a63c1a80ebe018",
    "documentType": "Dokument",
    "travelType": "Flyg",
    "departureDateTime": "2024-09-02T13:00:00",
    "travelFrom": "Sverige",
    "travelTo": "Senegal",
    "price": 18567,
    "travelTime": "06:30:00",
    "information": "2A",
    "vehicleNumber": "FJ45",
    "hoursDelayed": null,
    "arrivalDateTime": null,
    "delayed": false
  },
  {
    "id": "669e2f3be1a63c1a80ebe00f",
    "documentType": "Dokument",
    "travelType": "Tåg",
    "departureDateTime": "2024-09-02T15:35:00",
    "travelFrom": "Tyskland",
    "travelTo": "Frankrike",
    "price": 860,
    "travelTime": "09:20:00",
    "information": "SOVALKOV",
    "vehicleNumber": "T1233",
    "hoursDelayed": null,
    "arrivalDateTime": null,
    "delayed": false
  },
  {
    "id": "669e2f3be1a63c1a80ebe012",
    "documentType": "Dokument",
    "travelType": "Flyg",
    "departureDateTime": "2024-09-03T21:30:00",
    "travelFrom": "Venezuela",
    "travelTo": "Ecuador",
    "price": 3215,
    "travelTime": "05:20:00",
    "information": "6E",
    "vehicleNumber": "F032JH",
    "hoursDelayed": null,
    "arrivalDateTime": null,
    "delayed": false
  },
  {
    "id": "669e2f3be1a63c1a80ebe016",
    "documentType": "Dokument",
    "travelType": "Flyg",
    "departureDateTime": "2024-09-03T11:43:00",
    "travelFrom": "Marocko",
    "travelTo": "Venezuela",
    "price": 1243,
    "travelTime": "09:50:00",
    "information": "B30",
    "vehicleNumber": "TT5HF",
    "hoursDelayed": "22:30:00",
    "arrivalDateTime": null,
    "delayed": true
  },
  {
    "id": "669e4c26a420eb62d467e12f",
    "documentType": "Dokument",
    "travelType": "Flyg",
    "departureDateTime": "2024-09-01T07:27:00",
    "travelFrom": "Ecuador",
    "travelTo": "Toronto",
    "price": 5321,
    "travelTime": "07:20:00",
    "information": "B2",
    "vehicleNumber": "F01023S",
    "hoursDelayed": null,
    "arrivalDateTime": null,
    "delayed": false
  }
]